oneNeuron/__init__.py
oneNeuron/perceptron.py
perceptron_pypi_Jateendra-0.0.1.dist-info/LICENSE
perceptron_pypi_Jateendra-0.0.1.dist-info/METADATA
perceptron_pypi_Jateendra-0.0.1.dist-info/WHEEL
perceptron_pypi_Jateendra-0.0.1.dist-info/top_level.txt
perceptron_pypi_Jateendra-0.0.1.dist-info/RECORD
