Metadata-Version: 2.1
Name: perceptron-pypi-Jateendra
Version: 0.0.1
Summary: It is an implementation of Perceptron
Home-page: https://github.com/Jateendra/perceptron_pypi
Author: Jateendra
Author-email: jateendra.pradhan@gmail.com
License: UNKNOWN
Project-URL: Bug Tracker, https://github.com/Jateendra/perceptron_pypi/issues
Platform: UNKNOWN
Classifier: Programming Language :: Python :: 3
Classifier: License :: OSI Approved :: MIT License
Classifier: Operating System :: OS Independent
Requires-Python: >=3.7
License-File: LICENSE
Requires-Dist: numpy
Requires-Dist: tqdm
